[
    {
        "reference": "i18n-item1-ger",
        "title": null,
        "workflow": null,
        "metadata": {
            "acknowledgements": null,
            "scoring_type": "per-question"
        },
        "note": null,
        "source": null,
        "definition": {
            "widgets": [
                {
                    "reference": "i18n-item1-ger-q1"
                }
            ],
            "template": "dynamic"
        },
        "description": "",
        "status": "published",
        "questions": [
            {
                "reference": "i18n-item1-ger-q1",
                "type": "mcq"
            }
        ],
        "features": [],
        "tags": []
    },
    {
        "reference": "i18n-item2-ger",
        "title": null,
        "workflow": null,
        "metadata": {
            "acknowledgements": null,
            "scoring_type": "per-question"
        },
        "note": null,
        "source": null,
        "definition": {
            "widgets": [
                {
                    "reference": "i18n-item2-ger-q1"
                }
            ],
            "template": "dynamic"
        },
        "description": "",
        "status": "published",
        "questions": [
            {
                "reference": "i18n-item2-ger-q1",
                "type": "longtextV2"
            }
        ],
        "features": [],
        "tags": []
    },
    {
        "reference": "i18n-item3-ger",
        "title": null,
        "workflow": null,
        "metadata": {
            "acknowledgements": null,
            "scoring_type": "per-question"
        },
        "note": null,
        "source": null,
        "definition": {
            "widgets": [
                {
                    "reference": "i18n-item3-ger-q1"
                }
            ],
            "template": "dynamic"
        },
        "description": "",
        "status": "published",
        "questions": [
            {
                "reference": "i18n-item3-ger-q1",
                "type": "clozeassociation"
            }
        ],
        "features": [],
        "tags": []
    }
]